ExifRead_nocycle-3.0.1.data/scripts/EXIF.py
exifread/__init__.py
exifread/classes.py
exifread/exif_log.py
exifread/heic.py
exifread/utils.py
exifread/tags/__init__.py
exifread/tags/exif.py
exifread/tags/makernote/__init__.py
exifread/tags/makernote/apple.py
exifread/tags/makernote/canon.py
exifread/tags/makernote/casio.py
exifread/tags/makernote/fujifilm.py
exifread/tags/makernote/nikon.py
exifread/tags/makernote/olympus.py
ExifRead_nocycle-3.0.1.dist-info/LICENSE.txt
ExifRead_nocycle-3.0.1.dist-info/METADATA
ExifRead_nocycle-3.0.1.dist-info/WHEEL
ExifRead_nocycle-3.0.1.dist-info/top_level.txt
ExifRead_nocycle-3.0.1.dist-info/RECORD
