Metadata-Version: 2.1
Name: ExifRead-nocycle
Version: 3.0.1
Summary: Read Exif metadata from tiff and jpeg files.
Home-page: https://github.com/ianare/exif-py
Author: Ianaré Sévi
Author-email: ianare@gmail.com
License: BSD
Keywords: exif image metadata photo
Platform: UNKNOWN
Classifier: Development Status :: 5 - Production/Stable
Classifier: Environment :: Console
Classifier: Intended Audience :: Developers
Classifier: Intended Audience :: End Users/Desktop
Classifier: License :: OSI Approved :: BSD License
Classifier: Operating System :: OS Independent
Classifier: Programming Language :: Python :: 3.5
Classifier: Programming Language :: Python :: 3.6
Classifier: Programming Language :: Python :: 3.7
Classifier: Programming Language :: Python :: 3.8
Classifier: Topic :: Utilities
License-File: LICENSE.txt
